README.txt
setup.cfg
setup.py
chessmind/__init__.py
chessmind.core.egg-info/PKG-INFO
chessmind.core.egg-info/SOURCES.txt
chessmind.core.egg-info/dependency_links.txt
chessmind.core.egg-info/entry_points.txt
chessmind.core.egg-info/namespace_packages.txt
chessmind.core.egg-info/not-zip-safe
chessmind.core.egg-info/requires.txt
chessmind.core.egg-info/top_level.txt
chessmind/core/DEVELOPERS.txt
chessmind/core/TODO.txt
chessmind/core/__init__.py
chessmind/core/board.py
chessmind/core/definitions.py
chessmind/core/game.py
chessmind/core/piece.py
chessmind/core/position.py
docs/HISTORY.txt
