Metadata-Version: 1.0
Name: chessmind.core
Version: 0.3
Summary: Core ChessMind package
Home-page: http://maurits.vanrees.org/
Author: Maurits van Rees
Author-email: maurits@vanrees.org
License: GPL
Keywords: chess
Platform: UNKNOWN
Classifier: Programming Language :: Python
Classifier: Topic :: Software Development :: Libraries :: Python Modules
